LabuladongDeSuanfaXiaochao/README.md
LabuladongDeSuanfaXiaochao/__init__.py
LabuladongDeSuanfaXiaochao/__main__.py
LabuladongDeSuanfaXiaochao/file.epub
LabuladongDeSuanfaXiaochao/index.html
LabuladongDeSuanfaXiaochao/css/__init__.py
LabuladongDeSuanfaXiaochao/css/annotations.css
LabuladongDeSuanfaXiaochao/css/main.css
LabuladongDeSuanfaXiaochao/css/normalize.css
LabuladongDeSuanfaXiaochao/css/popup.css
LabuladongDeSuanfaXiaochao/font/__init__.py
LabuladongDeSuanfaXiaochao/font/fontello.eot
LabuladongDeSuanfaXiaochao/font/fontello.svg
LabuladongDeSuanfaXiaochao/font/fontello.ttf
LabuladongDeSuanfaXiaochao/font/fontello.woff
LabuladongDeSuanfaXiaochao/img/__init__.py
LabuladongDeSuanfaXiaochao/img/annotator-glyph-sprite.png
LabuladongDeSuanfaXiaochao/img/annotator-icon-sprite.png
LabuladongDeSuanfaXiaochao/img/apple-touch-icon.png
LabuladongDeSuanfaXiaochao/img/cancelfullscreen.png
LabuladongDeSuanfaXiaochao/img/close.png
LabuladongDeSuanfaXiaochao/img/fullscreen.png
LabuladongDeSuanfaXiaochao/img/loader.gif
LabuladongDeSuanfaXiaochao/img/menu-icon.png
LabuladongDeSuanfaXiaochao/img/save.png
LabuladongDeSuanfaXiaochao/img/saved.png
LabuladongDeSuanfaXiaochao/img/settings-s.png
LabuladongDeSuanfaXiaochao/img/settings.png
LabuladongDeSuanfaXiaochao/img/star.png
LabuladongDeSuanfaXiaochao/js/__init__.py
LabuladongDeSuanfaXiaochao/js/epub.js
LabuladongDeSuanfaXiaochao/js/epub.min.js
LabuladongDeSuanfaXiaochao/js/epub.min.map
LabuladongDeSuanfaXiaochao/js/hooks.min.js
LabuladongDeSuanfaXiaochao/js/hooks.min.map
LabuladongDeSuanfaXiaochao/js/reader.js
LabuladongDeSuanfaXiaochao/js/reader.js.map
LabuladongDeSuanfaXiaochao/js/reader.min.js
LabuladongDeSuanfaXiaochao/js/reader.min.map
LabuladongDeSuanfaXiaochao/js/hooks/__init__.py
LabuladongDeSuanfaXiaochao/js/hooks/extensions/__init__.py
LabuladongDeSuanfaXiaochao/js/hooks/extensions/highlight.js
LabuladongDeSuanfaXiaochao/js/libs/__init__.py
LabuladongDeSuanfaXiaochao/js/libs/jquery.min.js
labuladong_de_suanfa_xiaochao-2024.3.5.0.dist-info/METADATA
labuladong_de_suanfa_xiaochao-2024.3.5.0.dist-info/WHEEL
labuladong_de_suanfa_xiaochao-2024.3.5.0.dist-info/entry_points.txt
labuladong_de_suanfa_xiaochao-2024.3.5.0.dist-info/top_level.txt
labuladong_de_suanfa_xiaochao-2024.3.5.0.dist-info/RECORD
